LICENSE.txt
MANIFEST.in
README.txt
setup.py
Oasys_Canvas_Core.egg-info/PKG-INFO
Oasys_Canvas_Core.egg-info/SOURCES.txt
Oasys_Canvas_Core.egg-info/dependency_links.txt
Oasys_Canvas_Core.egg-info/requires.txt
Oasys_Canvas_Core.egg-info/top_level.txt
docs/index.rst
docs/make.bat
docs/source/conf.py
docs/source/index.rst
docs/source/orangecanvas/canvas.items.annotationitem.rst
docs/source/orangecanvas/canvas.items.linkitem.rst
docs/source/orangecanvas/canvas.items.nodeitem.rst
docs/source/orangecanvas/canvas.rst
docs/source/orangecanvas/canvas.scene.rst
docs/source/orangecanvas/document.quickmenu.rst
docs/source/orangecanvas/document.rst
docs/source/orangecanvas/document.schemeedit.rst
docs/source/orangecanvas/gui.dock.rst
docs/source/orangecanvas/gui.dropshadow.rst
docs/source/orangecanvas/gui.framelesswindow.rst
docs/source/orangecanvas/gui.lineedit.rst
docs/source/orangecanvas/gui.quickhelp.rst
docs/source/orangecanvas/gui.rst
docs/source/orangecanvas/gui.splashscreen.rst
docs/source/orangecanvas/gui.stackedwidget.rst
docs/source/orangecanvas/gui.toolbar.rst
docs/source/orangecanvas/gui.toolbox.rst
docs/source/orangecanvas/gui.toolgrid.rst
docs/source/orangecanvas/gui.tooltree.rst
docs/source/orangecanvas/index.rst
docs/source/orangecanvas/overview.rst
docs/source/orangecanvas/registry.rst
docs/source/orangecanvas/scheme.annotation.rst
docs/source/orangecanvas/scheme.link.rst
docs/source/orangecanvas/scheme.node.rst
docs/source/orangecanvas/scheme.readwrite.rst
docs/source/orangecanvas/scheme.rst
docs/source/orangecanvas/scheme.scheme.rst
orangecanvas/__init__.py
orangecanvas/__main__.py
orangecanvas/config.py
orangecanvas/main.py
orangecanvas/resources.py
orangecanvas/application/__init__.py
orangecanvas/application/aboutdialog.py
orangecanvas/application/addons.py
orangecanvas/application/application.py
orangecanvas/application/canvasmain.py
orangecanvas/application/canvastooldock.py
orangecanvas/application/outputview.py
orangecanvas/application/schemeinfo.py
orangecanvas/application/settings.py
orangecanvas/application/welcomedialog.py
orangecanvas/application/widgettoolbox.py
orangecanvas/application/tests/__init__.py
