Metadata-Version: 1.0
Name: Oasys-Canvas-Core
Version: 1.0.7
Summary: Core component of Oasys Canvas
Home-page: http://orange.biolab.si/
Author: Bioinformatics Laboratory, FRI UL
Author-email: lucarebuffi@elettra.eu
License: GPLv3
Platform: UNKNOWN
